asyncratelimiter/__init__.py
asyncratelimiter-1.0.0.dist-info/LICENSE
asyncratelimiter-1.0.0.dist-info/METADATA
asyncratelimiter-1.0.0.dist-info/WHEEL
asyncratelimiter-1.0.0.dist-info/top_level.txt
asyncratelimiter-1.0.0.dist-info/RECORD
