Metadata-Version: 2.1
Name: asyncratelimiter
Version: 1.0.0
Summary: "AsyncIO-enabled rate limiter - limit the rate of API calls!"
Home-page: https://github.com/Kiruse/PyAsyncRateLimiter
Author: Kiruse
Author-email: kiruse@kiruse.dev
License: MIT
Keywords: asyncio,rate limiter,requests
Platform: UNKNOWN
Requires-Python: >=3.6
License-File: LICENSE
Requires-Dist: requests (>=2.0)
Provides-Extra: test
Requires-Dist: pytest (>=6) ; extra == 'test'
Requires-Dist: pytest-asyncio (>=0.15) ; extra == 'test'
